git_py_stats/__init__.py
git_py_stats/arg_parser.py
git_py_stats/calendar_cmds.py
git_py_stats/config.py
git_py_stats/generate_cmds.py
git_py_stats/git_operations.py
git_py_stats/interactive_mode.py
git_py_stats/list_cmds.py
git_py_stats/main.py
git_py_stats/menu.py
git_py_stats/non_interactive_mode.py
git_py_stats/suggest_cmds.py
git_py_stats-0.2.0.data/data/share/man/man1/git-py-stats.1
git_py_stats-0.2.0.dist-info/licenses/LICENSE
git_py_stats-0.2.0.dist-info/METADATA
git_py_stats-0.2.0.dist-info/WHEEL
git_py_stats-0.2.0.dist-info/entry_points.txt
git_py_stats-0.2.0.dist-info/top_level.txt
git_py_stats-0.2.0.dist-info/RECORD
