Metadata-Version: 2.4
Name: git-py-stats
Version: 0.2.0
Summary: A Python Implementation of git-quick-stats
Home-page: https://github.com/git-quick-stats/git-py-stats
Author: Tom Ice
Author-email: contact@thomasice.com
License: MIT
Keywords: git stats statistics command-line
Classifier: Programming Language :: Python :: 3
Classifier: Operating System :: OS Independent
Requires-Python: >=3.8
License-File: LICENSE
Dynamic: author
Dynamic: author-email
Dynamic: classifier
Dynamic: description
Dynamic: description-content-type
Dynamic: home-page
Dynamic: keywords
Dynamic: license
Dynamic: license-file
Dynamic: requires-python
Dynamic: summary
